setup.py
thingdb/__init__.py
thingdb/closed.py
thingdb/encoder.py
thingdb/wrapper.py
thingdb.egg-info/PKG-INFO
thingdb.egg-info/SOURCES.txt
thingdb.egg-info/dependency_links.txt
thingdb.egg-info/not-zip-safe
thingdb.egg-info/top_level.txt