Metadata-Version: 1.0
Name: thingdb
Version: 4.0.0
Summary: Python database using dict's
Home-page: https://github.com/itslukej/thing
Author: Luke James
Author-email: me@lukej.me
License: GNU
Platform: UNKNOWN
